brd_serp_client/__init__.py
brd_serp_client/conf.py
brd_serp_client/example.py
brd_serp_client/info.py
brd_serp_client/scripts.py
brd_serp_client/utils.py
brd_serp_client/client/__init__.py
brd_serp_client/client/bing.py
brd_serp_client/client/core.py
brd_serp_client/client/google.py
brd_serp_client/model/__init__.py
brd_serp_client/model/core.py
brd_serp_client/model/google.py
brd_serp_client/schema/__init__.py
brd_serp_client/schema/google.py
brd_serp_client-0.0.6.dist-info/METADATA
brd_serp_client-0.0.6.dist-info/WHEEL
brd_serp_client-0.0.6.dist-info/entry_points.txt
brd_serp_client-0.0.6.dist-info/top_level.txt
brd_serp_client-0.0.6.dist-info/RECORD
