Metadata-Version: 2.1
Name: brd_serp_client
Version: 0.0.6
Author: Woojin Cho
Author-email: w.cho@cj.net
License: MIT License
Requires-Python: >=3.9
Requires-Dist: aiohttp
Requires-Dist: click
Requires-Dist: dasida
Requires-Dist: pillow
Requires-Dist: pydantic
